layoutimg/__init__.py
layoutimg/__main__.py
layoutimg/config.toml
layoutimg/layoutenv.py
layoutimg/layoutimg.py
layoutimg/layoutnode.py
layoutimg/setup.py
layoutimg/renderer/__init__.py
layoutimg/renderer/renderer.py
layout_image-0.2.0.dist-info/LICENSE
layout_image-0.2.0.dist-info/METADATA
layout_image-0.2.0.dist-info/WHEEL
layout_image-0.2.0.dist-info/entry_points.txt
layout_image-0.2.0.dist-info/top_level.txt
layout_image-0.2.0.dist-info/RECORD
