Metadata-Version: 2.1
Name: layout-image
Version: 0.2.0
Summary: A package for creating basic images with XML layouts
Author: Dirck van den Ende
License: MIT License
Project-URL: repository, https://github.com/dirckvdende/layout-image
Keywords: image,layout,XML,design
Classifier: License :: OSI Approved :: MIT License
Classifier: Programming Language :: Python
Classifier: Programming Language :: Python :: 3
Requires-Python: >=3.8
License-File: LICENSE
Requires-Dist: tomli
Requires-Dist: pillow
Provides-Extra: dev
Requires-Dist: pip-tools ; extra == 'dev'
Requires-Dist: pytest ; extra == 'dev'
